flask_pam/__init__.py
flask_pam/auth.py
flask_pam/token/__init__.py
flask_pam/token/jwt.py
flask_pam/token/simple.py
flask_pam/token/token.py
flask_pam/token_storage/__init__.py
flask_pam/token_storage/dict_storage.py
flask_pam/token_storage/token_storage.py
Flask_PAM_Reloaded-0.1.5.dist-info/LICENSE
Flask_PAM_Reloaded-0.1.5.dist-info/METADATA
Flask_PAM_Reloaded-0.1.5.dist-info/WHEEL
Flask_PAM_Reloaded-0.1.5.dist-info/top_level.txt
Flask_PAM_Reloaded-0.1.5.dist-info/RECORD
